br_docs/__init__.py
br_docs/cnpj.py
br_docs/cpf.py
br_docs/typing/__init__.py
br_docs/typing/cnpj.py
br_docs/typing/cpf.py
br_docs-0.0.9.dist-info/METADATA
br_docs-0.0.9.dist-info/WHEEL
br_docs-0.0.9.dist-info/licenses/LICENSE
br_docs-0.0.9.dist-info/RECORD
