Metadata-Version: 2.4
Name: br-docs
Version: 0.0.9
Summary: Brasil Documentation Utils and Validators
Project-URL: Homepage, https://github.com/fabioantonioastore/br-docs
Project-URL: Issues, https://github.com/fabioantonioastore/br-docs/issues
Project-URL: Documentation, https://github.com/fabioantonioastore/br-docs
Project-URL: Repository, https://github.com/fabioantonioastore/br-docs
Project-URL: Changelog, https://github.com/fabioantonioastore/br-docs
Author-email: Fabio Antonio Astore <astore.a.fabio@gmail.com>
License-Expression: MIT
License-File: LICENSE
Requires-Python: >=3.13.7
Provides-Extra: pydantic
Requires-Dist: pydantic; extra == 'pydantic'
